{
  "best_global_step": null,
  "best_metric": null,
  "best_model_checkpoint": null,
  "epoch": 3.0,
  "eval_steps": 500,
  "global_step": 96,
  "is_hyper_param_search": false,
  "is_local_process_zero": true,
  "is_world_process_zero": true,
  "log_history": [
    {
      "epoch": 0.3125,
      "grad_norm": 1.6451267004013062,
      "learning_rate": 9.062500000000001e-05,
      "loss": 2.2282,
      "step": 10
    },
    {
      "epoch": 0.625,
      "grad_norm": 1.0499948263168335,
      "learning_rate": 8.020833333333334e-05,
      "loss": 1.0554,
      "step": 20
    },
    {
      "epoch": 0.9375,
      "grad_norm": 0.8515449166297913,
      "learning_rate": 6.979166666666666e-05,
      "loss": 0.654,
      "step": 30
    },
    {
      "epoch": 1.25,
      "grad_norm": 0.6806955933570862,
      "learning_rate": 5.9375e-05,
      "loss": 0.6102,
      "step": 40
    },
    {
      "epoch": 1.5625,
      "grad_norm": 0.7483617067337036,
      "learning_rate": 4.8958333333333335e-05,
      "loss": 0.5231,
      "step": 50
    },
    {
      "epoch": 1.875,
      "grad_norm": 0.8631322383880615,
      "learning_rate": 3.854166666666667e-05,
      "loss": 0.4805,
      "step": 60
    },
    {
      "epoch": 2.1875,
      "grad_norm": 0.7878393530845642,
      "learning_rate": 2.8125000000000003e-05,
      "loss": 0.4202,
      "step": 70
    },
    {
      "epoch": 2.5,
      "grad_norm": 0.7547236084938049,
      "learning_rate": 1.7708333333333335e-05,
      "loss": 0.4238,
      "step": 80
    },
    {
      "epoch": 2.8125,
      "grad_norm": 0.9178236722946167,
      "learning_rate": 7.2916666666666674e-06,
      "loss": 0.4366,
      "step": 90
    }
  ],
  "logging_steps": 10,
  "max_steps": 96,
  "num_input_tokens_seen": 0,
  "num_train_epochs": 3,
  "save_steps": 500,
  "stateful_callbacks": {
    "TrainerControl": {
      "args": {
        "should_epoch_stop": false,
        "should_evaluate": false,
        "should_log": false,
        "should_save": true,
        "should_training_stop": true
      },
      "attributes": {}
    }
  },
  "total_flos": 744926330880000.0,
  "train_batch_size": 32,
  "trial_name": null,
  "trial_params": null
}
